[
    {
      "id": "king",
      "data": [
        {
          "targetWord": "land",
          "targetWords": [
            "queen",
            "people",
            "man",
            "country",
            "women",
            "religion",
            "nation"
          ],
          "similarities": [
            0.8678432156652545,
            0.8656321680024526,
            0.8306538941341034,
            0.7674283535144856,
            0.7610159274352528,
            0.7332627955698273,
            0.7005589899776488
          ]
        },
        {
          "targetWord": "queen",
          "targetWords": [
            "man",
            "people",
            "land",
            "women",
            "country",
            "religion",
            "nation"
          ],
          "similarities": [
            0.884062473699033,
            0.855267059041896,
            0.7246377963148393,
            0.7032581649257361,
            0.6733943888741769,
            0.6261840591422776,
            0.6188656464682023
          ]
        },
        {
          "targetWord": "man",
          "targetWords": [
            "queen",
            "people",
            "land",
            "women",
            "country",
            "religion",
            "nation"
          ],
          "similarities": [
            0.9409938514858432,
            0.8782898363898676,
            0.7404203626402314,
            0.7341973526203462,
            0.690049971999335,
            0.6527664603304446,
            0.6327397077709386
          ]
        },
        {
          "targetWord": "women",
          "targetWords": [
            "people",
            "queen",
            "man",
            "land",
            "nation",
            "country",
            "religion"
          ],
          "similarities": [
            0.885689141011217,
            0.8710478601974923,
            0.8486757647982069,
            0.7820342491513658,
            0.7636098111617958,
            0.7539468699382094,
            0.7077787091846774
          ]
        },
        {
          "targetWord": "people",
          "targetWords": [
            "queen",
            "man",
            "land",
            "women",
            "country",
            "nation",
            "religion"
          ],
          "similarities": [
            0.9226718723104358,
            0.8874108091358457,
            0.7800667164998497,
            0.7755561436152147,
            0.733446808125373,
            0.6902024655664731,
            0.6851601304354611
          ]
        },
        {
          "targetWord": "country",
          "targetWords": [
            "people",
            "queen",
            "man",
            "land",
            "nation",
            "women",
            "religion"
          ],
          "similarities": [
            0.8570503809975033,
            0.8492070121279957,
            0.8150198615681133,
            0.8076824825388891,
            0.7822880629552713,
            0.7736583775722226,
            0.7325558777047094
          ]
        },
        {
          "targetWord": "nation",
          "targetWords": [
            "people",
            "queen",
            "women",
            "country",
            "man",
            "land",
            "religion"
          ],
          "similarities": [
            0.8489737451502914,
            0.8300305114307502,
            0.8193172870051789,
            0.8138133930302776,
            0.7920993384845118,
            0.7732645998643948,
            0.714801501375656
          ]
        },
        {
          "targetWord": "religion",
          "targetWords": [
            "people",
            "queen",
            "man",
            "land",
            "country",
            "women",
            "nation"
          ],
          "similarities": [
            0.8477881983846663,
            0.8431954962477096,
            0.8187780952077067,
            0.8108002701745214,
            0.7684332443414565,
            0.7646216509608944,
            0.7184145859266762
          ]
        }
      ],
      "aboveThreshold": [
        "country",
        "land",
        "man",
        "nation",
        "people",
        "queen",
        "religion",
        "women"
      ]
    },
    {
      "id": "land",
      "data": [
        {
          "targetWord": "king",
          "targetWords": [
            "queen",
            "people",
            "man",
            "country",
            "women",
            "religion",
            "nation"
          ],
          "similarities": [
            0.8678432156652545,
            0.8656321680024526,
            0.8306538941341034,
            0.7674283535144856,
            0.7610159274352528,
            0.7332627955698273,
            0.7005589899776488
          ]
        },
        {
          "targetWord": "queen",
          "targetWords": [
            "king",
            "people",
            "man",
            "country",
            "women",
            "religion",
            "nation"
          ],
          "similarities": [
            0.9022601498772732,
            0.8682488287368008,
            0.8504163159663867,
            0.7603889348941949,
            0.7569692617653402,
            0.7292033247747013,
            0.6843854152283907
          ]
        },
        {
          "targetWord": "man",
          "targetWords": [
            "people",
            "king",
            "queen",
            "women",
            "country",
            "religion",
            "nation"
          ],
          "similarities": [
            0.8737436698105304,
            0.8630503345071133,
            0.8499191487803809,
            0.7726685849014355,
            0.7622789125104577,
            0.7415202782336686,
            0.6849090408271744
          ]
        },
        {
          "targetWord": "women",
          "targetWords": [
            "people",
            "country",
            "king",
            "nation",
            "religion",
            "man",
            "queen"
          ],
          "similarities": [
            0.8405343471788481,
            0.7892266451930249,
            0.7776925081397178,
            0.7772097369430272,
            0.7616483573786478,
            0.7607539826297981,
            0.7430019779846512
          ]
        },
        {
          "targetWord": "people",
          "targetWords": [
            "king",
            "man",
            "queen",
            "women",
            "country",
            "religion",
            "nation"
          ],
          "similarities": [
            0.8364227422797063,
            0.8127919306085862,
            0.8063073902103818,
            0.7939776926765878,
            0.7873966003825742,
            0.7574866656412859,
            0.7244478526140454
          ]
        },
        {
          "targetWord": "country",
          "targetWords": [
            "people",
            "nation",
            "religion",
            "women",
            "king",
            "man",
            "queen"
          ],
          "similarities": [
            0.8026420835003714,
            0.780732927492761,
            0.7688572247139094,
            0.7623218109661363,
            0.7540800125209461,
            0.7218935889244735,
            0.7174910706882924
          ]
        },
        {
          "targetWord": "nation",
          "targetWords": [
            "country",
            "women",
            "people",
            "religion",
            "king",
            "man",
            "queen"
          ],
          "similarities": [
            0.8387051740480717,
            0.8120385993231473,
            0.8009290324760827,
            0.7622075865023314,
            0.7476688239238077,
            0.7037172806541372,
            0.7008729451348701
          ]
        },
        {
          "targetWord": "religion",
          "targetWords": [
            "people",
            "country",
            "women",
            "king",
            "nation",
            "man",
            "queen"
          ],
          "similarities": [
            0.7841981341918918,
            0.7814621848892627,
            0.7466977608800006,
            0.7318338473692684,
            0.7156619383944609,
            0.7139693156638269,
            0.6987152599123665
          ]
        }
      ],
      "aboveThreshold": [
        "country",
        "king",
        "man",
        "nation",
        "people",
        "queen",
        "religion",
        "women"
      ]
    },
    {
      "id": "queen",
      "data": [
        {
          "targetWord": "king",
          "targetWords": [
            "man",
            "people",
            "land",
            "women",
            "country",
            "religion",
            "nation"
          ],
          "similarities": [
            0.884062473699033,
            0.855267059041896,
            0.7246377963148393,
            0.7032581649257361,
            0.6733943888741769,
            0.6261840591422776,
            0.6188656464682023
          ]
        },
        {
          "targetWord": "land",
          "targetWords": [
            "king",
            "people",
            "man",
            "country",
            "women",
            "religion",
            "nation"
          ],
          "similarities": [
            0.9022601498772732,
            0.8682488287368008,
            0.8504163159663867,
            0.7603889348941949,
            0.7569692617653402,
            0.7292033247747013,
            0.6843854152283907
          ]
        },
        {
          "targetWord": "man",
          "targetWords": [
            "king",
            "people",
            "women",
            "land",
            "country",
            "religion",
            "nation"
          ],
          "similarities": [
            0.9283816708306618,
            0.8663714464284717,
            0.7181997881805148,
            0.717552551325635,
            0.6719982469267697,
            0.6382878334058527,
            0.6065611603559019
          ]
        },
        {
          "targetWord": "women",
          "targetWords": [
            "king",
            "people",
            "man",
            "land",
            "country",
            "nation",
            "religion"
          ],
          "similarities": [
            0.8936567401155538,
            0.88444921261706,
            0.8653468581082117,
            0.7672936350550698,
            0.7434160404459847,
            0.7433006903792354,
            0.7005778824891934
          ]
        },
        {
          "targetWord": "people",
          "targetWords": [
            "king",
            "man",
            "women",
            "land",
            "country",
            "religion",
            "nation"
          ],
          "similarities": [
            0.9354072089710302,
            0.9004629895756762,
            0.7647744229624394,
            0.7620911107044475,
            0.720066467927042,
            0.6753570539545444,
            0.667531468141915
          ]
        },
        {
          "targetWord": "country",
          "targetWords": [
            "king",
            "people",
            "man",
            "land",
            "women",
            "nation",
            "religion"
          ],
          "similarities": [
            0.8773466803619613,
            0.8580454326731324,
            0.8328583514698052,
            0.7954119669803805,
            0.7682277701859853,
            0.7647587115910569,
            0.7272358336076717
          ]
        },
        {
          "targetWord": "nation",
          "targetWords": [
            "king",
            "people",
            "women",
            "man",
            "country",
            "land",
            "religion"
          ],
          "similarities": [
            0.8729277540494769,
            0.8545107546625279,
            0.8176004294778249,
            0.8152324440134209,
            0.8090331196185154,
            0.7645288111443856,
            0.7130145889986329
          ]
        },
        {
          "targetWord": "religion",
          "targetWords": [
            "king",
            "people",
            "man",
            "land",
            "country",
            "women",
            "nation"
          ],
          "similarities": [
            0.8654922595713918,
            0.8469831787774553,
            0.835733341016012,
            0.7960141722793419,
            0.7579464319908722,
            0.757223816807158,
            0.6986675566460762
          ]
        }
      ],
      "aboveThreshold": [
        "country",
        "king",
        "land",
        "man",
        "nation",
        "people",
        "religion",
        "women"
      ]
    },
    {
      "id": "man",
      "data": [
        {
          "targetWord": "king",
          "targetWords": [
            "queen",
            "people",
            "land",
            "women",
            "country",
            "religion",
            "nation"
          ],
          "similarities": [
            0.9409938514858432,
            0.8782898363898676,
            0.7404203626402314,
            0.7341973526203462,
            0.690049971999335,
            0.6527664603304446,
            0.6327397077709386
          ]
        },
        {
          "targetWord": "land",
          "targetWords": [
            "people",
            "king",
            "queen",
            "women",
            "country",
            "religion",
            "nation"
          ],
          "similarities": [
            0.8737436698105304,
            0.8630503345071133,
            0.8499191487803809,
            0.7726685849014355,
            0.7622789125104577,
            0.7415202782336686,
            0.6849090408271744
          ]
        },
        {
          "targetWord": "queen",
          "targetWords": [
            "king",
            "people",
            "women",
            "land",
            "country",
            "religion",
            "nation"
          ],
          "similarities": [
            0.9283816708306618,
            0.8663714464284717,
            0.7181997881805148,
            0.717552551325635,
            0.6719982469267697,
            0.6382878334058527,
            0.6065611603559019
          ]
        },
        {
          "targetWord": "women",
          "targetWords": [
            "people",
            "king",
            "queen",
            "land",
            "country",
            "nation",
            "religion"
          ],
          "similarities": [
            0.882331983173455,
            0.8459482799400955,
            0.8414652171766439,
            0.7613745250802991,
            0.7392459551596029,
            0.7367190036541522,
            0.7076206799308784
          ]
        },
        {
          "targetWord": "people",
          "targetWords": [
            "queen",
            "king",
            "women",
            "land",
            "country",
            "religion",
            "nation"
          ],
          "similarities": [
            0.8928106977636037,
            0.8913914203975679,
            0.7788795385184426,
            0.7606288974681819,
            0.720542206178918,
            0.6870227242712326,
            0.666412335810862
          ]
        },
        {
          "targetWord": "country",
          "targetWords": [
            "people",
            "king",
            "queen",
            "land",
            "women",
            "nation",
            "religion"
          ],
          "similarities": [
            0.8628491202268533,
            0.8386944539445996,
            0.8297807488969988,
            0.7950062909736154,
            0.7827897682543719,
            0.7636369978366764,
            0.7386976230060237
          ]
        },
        {
          "targetWord": "nation",
          "targetWords": [
            "people",
            "women",
            "king",
            "queen",
            "country",
            "land",
            "religion"
          ],
          "similarities": [
            0.8605866618827153,
            0.8332022093855571,
            0.8330735022552082,
            0.8150647922846713,
            0.8105395125733997,
            0.7653854094433397,
            0.7261287476773306
          ]
        },
        {
          "targetWord": "religion",
          "targetWords": [
            "people",
            "king",
            "queen",
            "land",
            "women",
            "country",
            "nation"
          ],
          "similarities": [
            0.8469839244680738,
            0.819862385929554,
            0.8159374910748475,
            0.7907045234378696,
            0.7679972824852721,
            0.7546315199575991,
            0.6941463200304308
          ]
        }
      ],
      "aboveThreshold": [
        "country",
        "king",
        "land",
        "nation",
        "people",
        "queen",
        "religion",
        "women"
      ]
    },
    {
      "id": "women",
      "data": [
        {
          "targetWord": "king",
          "targetWords": [
            "people",
            "queen",
            "man",
            "land",
            "nation",
            "country",
            "religion"
          ],
          "similarities": [
            0.885689141011217,
            0.8710478601974923,
            0.8486757647982069,
            0.7820342491513658,
            0.7636098111617958,
            0.7539468699382094,
            0.7077787091846774
          ]
        },
        {
          "targetWord": "land",
          "targetWords": [
            "people",
            "country",
            "king",
            "nation",
            "religion",
            "man",
            "queen"
          ],
          "similarities": [
            0.8405343471788481,
            0.7892266451930249,
            0.7776925081397178,
            0.7772097369430272,
            0.7616483573786478,
            0.7607539826297981,
            0.7430019779846512
          ]
        },
        {
          "targetWord": "queen",
          "targetWords": [
            "king",
            "people",
            "man",
            "land",
            "country",
            "nation",
            "religion"
          ],
          "similarities": [
            0.8936567401155538,
            0.88444921261706,
            0.8653468581082117,
            0.7672936350550698,
            0.7434160404459847,
            0.7433006903792354,
            0.7005778824891934
          ]
        },
        {
          "targetWord": "man",
          "targetWords": [
            "people",
            "king",
            "queen",
            "land",
            "country",
            "nation",
            "religion"
          ],
          "similarities": [
            0.882331983173455,
            0.8459482799400955,
            0.8414652171766439,
            0.7613745250802991,
            0.7392459551596029,
            0.7367190036541522,
            0.7076206799308784
          ]
        },
        {
          "targetWord": "people",
          "targetWords": [
            "man",
            "king",
            "queen",
            "land",
            "nation",
            "country",
            "religion"
          ],
          "similarities": [
            0.8189788373804592,
            0.8178904332036262,
            0.7961833342443018,
            0.7806725642214162,
            0.7781054812806506,
            0.7641718316995653,
            0.7229323968672862
          ]
        },
        {
          "targetWord": "country",
          "targetWords": [
            "nation",
            "people",
            "land",
            "religion",
            "king",
            "man",
            "queen"
          ],
          "similarities": [
            0.8417906430441205,
            0.8200365904416529,
            0.7888889725385534,
            0.7487565686693556,
            0.7461158889681279,
            0.735675780573017,
            0.7164760528002921
          ]
        },
        {
          "targetWord": "nation",
          "targetWords": [
            "country",
            "people",
            "land",
            "religion",
            "king",
            "man",
            "queen"
          ],
          "similarities": [
            0.7973260156291931,
            0.7867700459328912,
            0.7330533835626296,
            0.7111934076687298,
            0.7096076304094976,
            0.6891113068617377,
            0.6713620306120773
          ]
        },
        {
          "targetWord": "religion",
          "targetWords": [
            "people",
            "land",
            "nation",
            "country",
            "man",
            "king",
            "queen"
          ],
          "similarities": [
            0.8061574695153227,
            0.7878697725663674,
            0.78128944965339,
            0.7752844100564915,
            0.7321518010165896,
            0.7266988212712554,
            0.7008339460684874
          ]
        }
      ],
      "aboveThreshold": [
        "country",
        "king",
        "land",
        "man",
        "nation",
        "people",
        "queen",
        "religion"
      ]
    },
    {
      "id": "people",
      "data": [
        {
          "targetWord": "king",
          "targetWords": [
            "queen",
            "man",
            "land",
            "women",
            "country",
            "nation",
            "religion"
          ],
          "similarities": [
            0.9226718723104358,
            0.8874108091358457,
            0.7800667164998497,
            0.7755561436152147,
            0.733446808125373,
            0.6902024655664731,
            0.6851601304354611
          ]
        },
        {
          "targetWord": "land",
          "targetWords": [
            "king",
            "man",
            "queen",
            "women",
            "country",
            "religion",
            "nation"
          ],
          "similarities": [
            0.8364227422797063,
            0.8127919306085862,
            0.8063073902103818,
            0.7939776926765878,
            0.7873966003825742,
            0.7574866656412859,
            0.7244478526140454
          ]
        },
        {
          "targetWord": "queen",
          "targetWords": [
            "king",
            "man",
            "women",
            "land",
            "country",
            "religion",
            "nation"
          ],
          "similarities": [
            0.9354072089710302,
            0.9004629895756762,
            0.7647744229624394,
            0.7620911107044475,
            0.720066467927042,
            0.6753570539545444,
            0.667531468141915
          ]
        },
        {
          "targetWord": "man",
          "targetWords": [
            "queen",
            "king",
            "women",
            "land",
            "country",
            "religion",
            "nation"
          ],
          "similarities": [
            0.8928106977636037,
            0.8913914203975679,
            0.7788795385184426,
            0.7606288974681819,
            0.720542206178918,
            0.6870227242712326,
            0.666412335810862
          ]
        },
        {
          "targetWord": "women",
          "targetWords": [
            "man",
            "king",
            "queen",
            "land",
            "nation",
            "country",
            "religion"
          ],
          "similarities": [
            0.8189788373804592,
            0.8178904332036262,
            0.7961833342443018,
            0.7806725642214162,
            0.7781054812806506,
            0.7641718316995653,
            0.7229323968672862
          ]
        },
        {
          "targetWord": "country",
          "targetWords": [
            "land",
            "king",
            "nation",
            "women",
            "man",
            "queen",
            "religion"
          ],
          "similarities": [
            0.8110473742841878,
            0.8088747458205835,
            0.8005756299968309,
            0.8004925306417444,
            0.7920712953963476,
            0.7835885672110723,
            0.751117952581362
          ]
        },
        {
          "targetWord": "nation",
          "targetWords": [
            "women",
            "country",
            "king",
            "land",
            "man",
            "queen",
            "religion"
          ],
          "similarities": [
            0.8457685798715797,
            0.827003864941322,
            0.794743647352537,
            0.7753399798473677,
            0.766484824742865,
            0.7595318537635891,
            0.7329126377116083
          ]
        },
        {
          "targetWord": "religion",
          "targetWords": [
            "land",
            "king",
            "man",
            "women",
            "country",
            "queen",
            "nation"
          ],
          "similarities": [
            0.8126943462253909,
            0.7933811094619388,
            0.7928844360702246,
            0.7914047410267803,
            0.7818480143037025,
            0.772241531592891,
            0.7363918962145074
          ]
        }
      ],
      "aboveThreshold": [
        "country",
        "king",
        "land",
        "man",
        "nation",
        "queen",
        "religion",
        "women"
      ]
    },
    {
      "id": "country",
      "data": [
        {
          "targetWord": "king",
          "targetWords": [
            "people",
            "queen",
            "man",
            "land",
            "nation",
            "women",
            "religion"
          ],
          "similarities": [
            0.8570503809975033,
            0.8492070121279957,
            0.8150198615681133,
            0.8076824825388891,
            0.7822880629552713,
            0.7736583775722226,
            0.7325558777047094
          ]
        },
        {
          "targetWord": "land",
          "targetWords": [
            "people",
            "nation",
            "religion",
            "women",
            "king",
            "man",
            "queen"
          ],
          "similarities": [
            0.8026420835003714,
            0.780732927492761,
            0.7688572247139094,
            0.7623218109661363,
            0.7540800125209461,
            0.7218935889244735,
            0.7174910706882924
          ]
        },
        {
          "targetWord": "queen",
          "targetWords": [
            "king",
            "people",
            "man",
            "land",
            "women",
            "nation",
            "religion"
          ],
          "similarities": [
            0.8773466803619613,
            0.8580454326731324,
            0.8328583514698052,
            0.7954119669803805,
            0.7682277701859853,
            0.7647587115910569,
            0.7272358336076717
          ]
        },
        {
          "targetWord": "man",
          "targetWords": [
            "people",
            "king",
            "queen",
            "land",
            "women",
            "nation",
            "religion"
          ],
          "similarities": [
            0.8628491202268533,
            0.8386944539445996,
            0.8297807488969988,
            0.7950062909736154,
            0.7827897682543719,
            0.7636369978366764,
            0.7386976230060237
          ]
        },
        {
          "targetWord": "women",
          "targetWords": [
            "nation",
            "people",
            "land",
            "religion",
            "king",
            "man",
            "queen"
          ],
          "similarities": [
            0.8417906430441205,
            0.8200365904416529,
            0.7888889725385534,
            0.7487565686693556,
            0.7461158889681279,
            0.735675780573017,
            0.7164760528002921
          ]
        },
        {
          "targetWord": "people",
          "targetWords": [
            "land",
            "king",
            "nation",
            "women",
            "man",
            "queen",
            "religion"
          ],
          "similarities": [
            0.8110473742841878,
            0.8088747458205835,
            0.8005756299968309,
            0.8004925306417444,
            0.7920712953963476,
            0.7835885672110723,
            0.751117952581362
          ]
        },
        {
          "targetWord": "nation",
          "targetWords": [
            "women",
            "people",
            "land",
            "religion",
            "king",
            "man",
            "queen"
          ],
          "similarities": [
            0.7845025763106268,
            0.7569131268413475,
            0.7505132795801187,
            0.7253027856976066,
            0.6944903240579245,
            0.6590774124385252,
            0.6544326082604811
          ]
        },
        {
          "targetWord": "religion",
          "targetWords": [
            "land",
            "nation",
            "people",
            "women",
            "king",
            "man",
            "queen"
          ],
          "similarities": [
            0.7996631919561552,
            0.7860247364956455,
            0.7717139744574647,
            0.7529437854602006,
            0.7077807914934079,
            0.6961733649226045,
            0.6793080481585468
          ]
        }
      ],
      "aboveThreshold": [
        "king",
        "land",
        "man",
        "nation",
        "people",
        "queen",
        "religion",
        "women"
      ]
    },
    {
      "id": "nation",
      "data": [
        {
          "targetWord": "king",
          "targetWords": [
            "people",
            "queen",
            "women",
            "country",
            "man",
            "land",
            "religion"
          ],
          "similarities": [
            0.8489737451502914,
            0.8300305114307502,
            0.8193172870051789,
            0.8138133930302776,
            0.7920993384845118,
            0.7732645998643948,
            0.714801501375656
          ]
        },
        {
          "targetWord": "land",
          "targetWords": [
            "country",
            "women",
            "people",
            "religion",
            "king",
            "man",
            "queen"
          ],
          "similarities": [
            0.8387051740480717,
            0.8120385993231473,
            0.8009290324760827,
            0.7622075865023314,
            0.7476688239238077,
            0.7037172806541372,
            0.7008729451348701
          ]
        },
        {
          "targetWord": "queen",
          "targetWords": [
            "king",
            "people",
            "women",
            "man",
            "country",
            "land",
            "religion"
          ],
          "similarities": [
            0.8729277540494769,
            0.8545107546625279,
            0.8176004294778249,
            0.8152324440134209,
            0.8090331196185154,
            0.7645288111443856,
            0.7130145889986329
          ]
        },
        {
          "targetWord": "man",
          "targetWords": [
            "people",
            "women",
            "king",
            "queen",
            "country",
            "land",
            "religion"
          ],
          "similarities": [
            0.8605866618827153,
            0.8332022093855571,
            0.8330735022552082,
            0.8150647922846713,
            0.8105395125733997,
            0.7653854094433397,
            0.7261287476773306
          ]
        },
        {
          "targetWord": "women",
          "targetWords": [
            "country",
            "people",
            "land",
            "religion",
            "king",
            "man",
            "queen"
          ],
          "similarities": [
            0.7973260156291931,
            0.7867700459328912,
            0.7330533835626296,
            0.7111934076687298,
            0.7096076304094976,
            0.6891113068617377,
            0.6713620306120773
          ]
        },
        {
          "targetWord": "people",
          "targetWords": [
            "women",
            "country",
            "king",
            "land",
            "man",
            "queen",
            "religion"
          ],
          "similarities": [
            0.8457685798715797,
            0.827003864941322,
            0.794743647352537,
            0.7753399798473677,
            0.766484824742865,
            0.7595318537635891,
            0.7329126377116083
          ]
        },
        {
          "targetWord": "country",
          "targetWords": [
            "women",
            "people",
            "land",
            "religion",
            "king",
            "man",
            "queen"
          ],
          "similarities": [
            0.7845025763106268,
            0.7569131268413475,
            0.7505132795801187,
            0.7253027856976066,
            0.6944903240579245,
            0.6590774124385252,
            0.6544326082604811
          ]
        },
        {
          "targetWord": "religion",
          "targetWords": [
            "country",
            "women",
            "land",
            "people",
            "king",
            "man",
            "queen"
          ],
          "similarities": [
            0.8191021776461641,
            0.7949219025758543,
            0.7677671138011705,
            0.760561677963581,
            0.6916308304025012,
            0.6695317661735176,
            0.6536625369228333
          ]
        }
      ],
      "aboveThreshold": [
        "country",
        "king",
        "land",
        "man",
        "people",
        "queen",
        "religion",
        "women"
      ]
    },
    {
      "id": "religion",
      "data": [
        {
          "targetWord": "king",
          "targetWords": [
            "people",
            "queen",
            "man",
            "land",
            "country",
            "women",
            "nation"
          ],
          "similarities": [
            0.8477881983846663,
            0.8431954962477096,
            0.8187780952077067,
            0.8108002701745214,
            0.7684332443414565,
            0.7646216509608944,
            0.7184145859266762
          ]
        },
        {
          "targetWord": "land",
          "targetWords": [
            "people",
            "country",
            "women",
            "king",
            "nation",
            "man",
            "queen"
          ],
          "similarities": [
            0.7841981341918918,
            0.7814621848892627,
            0.7466977608800006,
            0.7318338473692684,
            0.7156619383944609,
            0.7139693156638269,
            0.6987152599123665
          ]
        },
        {
          "targetWord": "queen",
          "targetWords": [
            "king",
            "people",
            "man",
            "land",
            "country",
            "women",
            "nation"
          ],
          "similarities": [
            0.8654922595713918,
            0.8469831787774553,
            0.835733341016012,
            0.7960141722793419,
            0.7579464319908722,
            0.757223816807158,
            0.6986675566460762
          ]
        },
        {
          "targetWord": "man",
          "targetWords": [
            "people",
            "king",
            "queen",
            "land",
            "women",
            "country",
            "nation"
          ],
          "similarities": [
            0.8469839244680738,
            0.819862385929554,
            0.8159374910748475,
            0.7907045234378696,
            0.7679972824852721,
            0.7546315199575991,
            0.6941463200304308
          ]
        },
        {
          "targetWord": "women",
          "targetWords": [
            "people",
            "land",
            "nation",
            "country",
            "man",
            "king",
            "queen"
          ],
          "similarities": [
            0.8061574695153227,
            0.7878697725663674,
            0.78128944965339,
            0.7752844100564915,
            0.7321518010165896,
            0.7266988212712554,
            0.7008339460684874
          ]
        },
        {
          "targetWord": "people",
          "targetWords": [
            "land",
            "king",
            "man",
            "women",
            "country",
            "queen",
            "nation"
          ],
          "similarities": [
            0.8126943462253909,
            0.7933811094619388,
            0.7928844360702246,
            0.7914047410267803,
            0.7818480143037025,
            0.772241531592891,
            0.7363918962145074
          ]
        },
        {
          "targetWord": "country",
          "targetWords": [
            "land",
            "nation",
            "people",
            "women",
            "king",
            "man",
            "queen"
          ],
          "similarities": [
            0.7996631919561552,
            0.7860247364956455,
            0.7717139744574647,
            0.7529437854602006,
            0.7077807914934079,
            0.6961733649226045,
            0.6793080481585468
          ]
        },
        {
          "targetWord": "nation",
          "targetWords": [
            "country",
            "women",
            "land",
            "people",
            "king",
            "man",
            "queen"
          ],
          "similarities": [
            0.8191021776461641,
            0.7949219025758543,
            0.7677671138011705,
            0.760561677963581,
            0.6916308304025012,
            0.6695317661735176,
            0.6536625369228333
          ]
        }
      ],
      "aboveThreshold": [
        "country",
        "king",
        "land",
        "man",
        "nation",
        "people",
        "queen",
        "women"
      ]
    }
  ]